LICENSE.md
MANIFEST.in
README.md
setup.py
docs/Makefile
docs/source/ansible.rst
docs/source/client.rst
docs/source/conf.py
docs/source/index.rst
docs/source/mist.client.rst
docs/source/mist.cmd.helpers.rst
docs/source/mist.cmd.rst
docs/source/mist.rst
docs/source/modules.rst
docs/source/ansible/getting_started.rst
docs/source/ansible/mist_backends_module.rst
docs/source/ansible/mist_images_module.rst
docs/source/ansible/mist_keys_module.rst
docs/source/ansible/mist_locations_module.rst
docs/source/ansible/mist_module.rst
docs/source/ansible/mist_providers_module.rst
docs/source/ansible/mist_sizes_module.rst
docs/source/client/backends.rst
docs/source/client/getting_started.rst
docs/source/client/index.rst
docs/source/client/installation.rst
docs/source/client/keys.rst
docs/source/client/machines.rst
docs/source/client/monitoring.rst
docs/source/cmd/cmd.rst
docs/source/cmd/cmd_backend.rst
docs/source/cmd/cmd_key.rst
docs/source/cmd/cmd_machine.rst
docs/source/cmd/cmd_monitor.rst
docs/source/cmd/cmd_run.rst
docs/source/cmd/index.rst
docs/source/cmd/sync.rst
docs/source/notes/changelog.rst
docs/source/notes/roadmap.rst
docs/source/quickstart/python.rst
examples/multi-provision.py
src/mist.egg-info/PKG-INFO
src/mist.egg-info/SOURCES.txt
src/mist.egg-info/dependency_links.txt
src/mist.egg-info/not-zip-safe
src/mist.egg-info/requires.txt
src/mist.egg-info/top_level.txt
src/mistansible/__init__.py
src/mistansible/helpers.py
src/mistansible/mistplay
src/mistansible/mist.modules/mist
src/mistansible/mist.modules/mist_backends
src/mistansible/mist.modules/mist_images
src/mistansible/mist.modules/mist_keys
src/mistansible/mist.modules/mist_locations
src/mistansible/mist.modules/mist_providers
src/mistansible/mist.modules/mist_register
src/mistansible/mist.modules/mist_sizes
src/mistclient/__init__.py
src/mistclient/helpers.py
src/mistclient/model.py
src/mistcommand/__init__.py
src/mistcommand/mist
src/mistcommand/helpers/__init__.py
src/mistcommand/helpers/clouds.py
src/mistcommand/helpers/images.py
src/mistcommand/helpers/keys.py
src/mistcommand/helpers/locations.py
src/mistcommand/helpers/login.py
src/mistcommand/helpers/machines.py
