Metadata-Version: 1.1
Name: mist
Version: 1.9
Summary: Python client for mist.io
Home-page: https://github.com/mistio/mist.client
Author: Chris Loukas
Author-email: commixon@mist.io
License: GPLv3
Keywords: web cloud server management monitoring automation mobile libcloud pyramid amazon aws rackspace openstack linode softlayer digitalocean gce
Platform: UNKNOWN
Classifier: Programming Language :: Python
Classifier: Framework :: Pylons
Classifier: Topic :: Internet :: WWW/HTTP
Classifier: License :: OSI Approved :: GNU Affero General Public License v3
Classifier: Topic :: Internet :: WWW/HTTP :: WSGI :: Application
